nejimaki/__init__.py
nejimaki/cmd.py
nejimaki-0.1.2.dist-info/DESCRIPTION.rst
nejimaki-0.1.2.dist-info/entry_points.txt
nejimaki-0.1.2.dist-info/METADATA
nejimaki-0.1.2.dist-info/metadata.json
nejimaki-0.1.2.dist-info/RECORD
nejimaki-0.1.2.dist-info/top_level.txt
nejimaki-0.1.2.dist-info/WHEEL
