Metadata-Version: 2.0
Name: nejimaki
Version: 0.1.2
Summary: emit files from one yaml file
Home-page: https://github.com/podhmo/nejimaki
Author: podhmo
Author-email: ababjam61@gmail.com
License: UNKNOWN
Platform: UNKNOWN
Classifier: Programming Language :: Python
Classifier: Programming Language :: Python :: Implementation :: CPython
Requires-Dist: dictknife[load]
Provides-Extra: docs
Provides-Extra: testing
